xia_agent/__init__.py
xia_agent/agent.cpython-311-darwin.so
xia_agent-0.1.7.dist-info/LICENSE.txt
xia_agent-0.1.7.dist-info/METADATA
xia_agent-0.1.7.dist-info/WHEEL
xia_agent-0.1.7.dist-info/top_level.txt
xia_agent-0.1.7.dist-info/RECORD
